datasetsconverter/__init__.py
datasetsconverter/conversions.py
datasetsconverter-0.0.1.dist-info/licenses/LICENSE.txt
datasetsconverter-0.0.1.dist-info/METADATA
datasetsconverter-0.0.1.dist-info/WHEEL
datasetsconverter-0.0.1.dist-info/top_level.txt
datasetsconverter-0.0.1.dist-info/RECORD
