Metadata-Version: 2.4
Name: datasetsconverter
Version: 0.0.1
Summary: A Python package for converting object detection datasets between COCO, YOLO, and PASCAL VOC formats.
Download-URL: https://github.com/george-mountain/datasetsconverter/releases/tag/0.0.1
Author: George Mountain
Author-email: George Mountain <engrmountain@gmail.com>
License-Expression: MIT
Project-URL: DOWNLOAD, https://github.com/george-mountain/datasetsconverter/releases/tag/0.0.1
Keywords: dataset,conversion,COCO,YOLO,PASCAL VOC
Classifier: Development Status :: 3 - Alpha
Classifier: Intended Audience :: Developers
Classifier: Programming Language :: Python :: 3
Classifier: Programming Language :: Python :: 3.7
Classifier: Programming Language :: Python :: 3.8
Classifier: Programming Language :: Python :: 3.9
Classifier: Programming Language :: Python :: 3.10
Classifier: Programming Language :: Python :: 3.11
Classifier: Programming Language :: Python :: 3.12
Classifier: Programming Language :: Python :: 3.13
License-File: LICENSE.txt
Requires-Dist: tqdm
Requires-Dist: pillow
Dynamic: author
Dynamic: download-url
Dynamic: license-file
